csort
csort.py
setup.py
csort.egg-info/PKG-INFO
csort.egg-info/SOURCES.txt
csort.egg-info/dependency_links.txt
csort.egg-info/requires.txt
csort.egg-info/top_level.txt