Metadata-Version: 1.1
Name: csort
Version: 0.1.1
Summary: sort columns
Home-page: https://github.com/tototoshi/csort
Author: Toshiyuki Takahashi
Author-email: t.toshi.0412 at gmail.com
License: BSD
Keywords: tsv
Platform: POSIX
Platform: Windows
Classifier: License :: OSI Approved :: BSD License
Classifier: Programming Language :: Python
Classifier: Development Status :: 4 - Beta
Classifier: Environment :: Console
Classifier: Intended Audience :: Developers
Classifier: Topic :: Utilities 
Classifier: Topic :: Software Development
